wcorr/__init__.py
wcorr/wcorr.py
wcorr-2.2.dist-info/LICENSE
wcorr-2.2.dist-info/WHEEL
wcorr-2.2.dist-info/METADATA
wcorr-2.2.dist-info/RECORD
