Metadata-Version: 2.1
Name: wcorr
Version: 2.2
Summary: Weighted correlation in Python. Pandas based implementation of weighted Pearson and Spearman correlations.
Author-email: matthijsz <m.d.vander.zee@vu.nl>, yvictor <yvictor3141@gmail.com>
Classifier: License :: OSI Approved :: MIT License
Project-URL: Home, https://github.com/Yvictor/weightedcorr
